pynequa/__init__.py
pynequa/core.py
pynequa/models.py
pynequa/api/__init__.py
pynequa/api/api.py
pynequa-0.2.0.dist-info/LICENSE
pynequa-0.2.0.dist-info/METADATA
pynequa-0.2.0.dist-info/WHEEL
pynequa-0.2.0.dist-info/top_level.txt
pynequa-0.2.0.dist-info/RECORD
