Metadata-Version: 2.1
Name: pynequa
Version: 0.2.0
Summary: Pythonic Layer for Sinequa REST API
Author: Anish Bhusal
Author-email: Anish Bhusal <anish.bhusal@uah.edu>
Project-URL: Homepage, https://github.com/NASA-IMPACT/pynequa
Classifier: Programming Language :: Python :: 3
Classifier: License :: OSI Approved :: MIT License
Classifier: Operating System :: OS Independent
Requires-Python: >=3.7
License-File: LICENSE
